{"skeleton":{"hash":"EvYGTppmeU94b+Kc+Z09hJzCLU0","spine":"3.6.37","width":250,"height":79},"bones":[{"name":"root"},{"name":"bone","parent":"root","scaleX":6,"scaleY":6},{"name":"bone2","parent":"root","x":4.72,"y":-7.09,"scaleX":6,"scaleY":6},{"name":"bone3","parent":"root"},{"name":"bone4","parent":"root","y":16.6,"scaleX":8,"scaleY":8}],"slots":[{"name":"FXGranada","bone":"bone"},{"name":"FXGranada2","bone":"bone2"},{"name":"sombra","bone":"bone3","attachment":"sombra"},{"name":"polvo","bone":"bone4"}],"skins":{"default":{"FXGranada":{"granada/granada_00003":{"x":12,"y":107,"width":250,"height":216},"granada/granada_00004":{"x":12,"y":107,"width":250,"height":216},"granada/granada_00005":{"x":12,"y":107,"width":250,"height":216},"granada/granada_00006":{"x":12,"y":107,"width":250,"height":216},"granada/granada_00007":{"x":12,"y":107,"width":250,"height":216},"granada/granada_00008":{"x":12,"y":107,"width":250,"height":216},"granada/granada_00009":{"x":12,"y":107,"width":250,"height":216},"granada/granada_00010":{"x":12,"y":107,"width":250,"height":216},"granada/granada_00011":{"x":12,"y":107,"width":250,"height":216},"granada/granada_00012":{"x":12,"y":107,"width":250,"height":216},"granada/granada_00013":{"x":12,"y":107,"width":250,"height":216},"granada/granada_00014":{"x":12,"y":107,"width":250,"height":216},"granada/granada_00015":{"x":12,"y":107,"width":250,"height":216},"granada/granada_00016":{"x":12,"y":107,"width":250,"height":216},"granada/granada_00017":{"x":12,"y":107,"width":250,"height":216},"granada/granada_00018":{"x":12,"y":107,"width":250,"height":216},"granada/granada_00019":{"x":12,"y":107,"width":250,"height":216},"granada/granada_00020":{"x":12,"y":107,"width":250,"height":216},"granada/granada_00021":{"x":12,"y":107,"width":250,"height":216},"granada/granada_00022":{"x":12,"y":107,"width":250,"height":216},"granada/granada_00023":{"x":12,"y":107,"width":250,"height":216},"granada/granada_00024":{"x":12,"y":107,"width":250,"height":216},"granada/granada_00025":{"x":12,"y":107,"width":250,"height":216},"granada/granada_00026":{"x":12,"y":107,"width":250,"height":216},"granada/granada_00027":{"x":12,"y":107,"width":250,"height":216},"granada/granada_00028":{"x":12,"y":107,"width":250,"height":216},"granada/granada_00029":{"x":12,"y":107,"width":250,"height":216},"granada/granada_00030":{"x":12,"y":107,"width":250,"height":216},"granada/granada_00031":{"x":12,"y":107,"width":250,"height":216},"granada/granada_00032":{"x":12,"y":107,"width":250,"height":216},"granada/granada_00033":{"x":12,"y":107,"width":250,"height":216},"granada/granada_00034":{"x":12,"y":107,"width":250,"height":216},"granada/granada_00035":{"x":12,"y":107,"width":250,"height":216}},"FXGranada2":{"granada2/granada2_00002":{"x":9.1,"y":105.7,"width":250,"height":209},"granada2/granada2_00003":{"x":9.1,"y":105.7,"width":250,"height":209},"granada2/granada2_00004":{"x":9.1,"y":105.7,"width":250,"height":209},"granada2/granada2_00005":{"x":9.1,"y":105.7,"width":250,"height":209},"granada2/granada2_00006":{"x":9.1,"y":105.7,"width":250,"height":209},"granada2/granada2_00007":{"x":9.1,"y":105.7,"width":250,"height":209},"granada2/granada2_00008":{"x":9.1,"y":105.7,"width":250,"height":209},"granada2/granada2_00009":{"x":9.1,"y":105.7,"width":250,"height":209},"granada2/granada2_00010":{"x":9.1,"y":105.7,"width":250,"height":209},"granada2/granada2_00011":{"x":9.1,"y":105.7,"width":250,"height":209},"granada2/granada2_00012":{"x":9.1,"y":105.7,"width":250,"height":209},"granada2/granada2_00013":{"x":9.1,"y":105.7,"width":250,"height":209},"granada2/granada2_00014":{"x":9.1,"y":105.7,"width":250,"height":209},"granada2/granada2_00015":{"x":9.1,"y":105.7,"width":250,"height":209},"granada2/granada2_00016":{"x":9.1,"y":105.7,"width":250,"height":209},"granada2/granada2_00017":{"x":9.1,"y":105.7,"width":250,"height":209},"granada2/granada2_00018":{"x":9.1,"y":105.7,"width":250,"height":209},"granada2/granada2_00019":{"x":9.1,"y":105.7,"width":250,"height":209},"granada2/granada2_00020":{"x":9.1,"y":105.7,"width":250,"height":209},"granada2/granada2_00021":{"x":9.1,"y":105.7,"width":250,"height":209},"granada2/granada2_00022":{"x":9.1,"y":105.7,"width":250,"height":209},"granada2/granada2_00023":{"x":9.1,"y":105.7,"width":250,"height":209},"granada2/granada2_00024":{"x":9.1,"y":105.7,"width":250,"height":209},"granada2/granada2_00025":{"x":9.1,"y":105.7,"width":250,"height":209},"granada2/granada2_00026":{"x":9.1,"y":105.7,"width":250,"height":209},"granada2/granada2_00027":{"x":9.1,"y":105.7,"width":250,"height":209},"granada2/granada2_00028":{"x":9.1,"y":105.7,"width":250,"height":209},"granada2/granada2_00029":{"x":9.1,"y":105.7,"width":250,"height":209},"granada2/granada2_00030":{"x":9.1,"y":105.7,"width":250,"height":209},"granada2/granada2_00031":{"x":9.1,"y":105.7,"width":250,"height":209},"granada2/granada2_00032":{"x":9.1,"y":105.7,"width":250,"height":209},"granada2/granada2_00033":{"x":9.1,"y":105.7,"width":250,"height":209},"granada2/granada2_00034":{"x":9.1,"y":105.7,"width":250,"height":209},"granada2/granada2_00035":{"x":9.1,"y":105.7,"width":250,"height":209},"granada2/granada2_00036":{"x":9.1,"y":105.7,"width":250,"height":209},"granada2/granada2_00037":{"x":9.1,"y":105.7,"width":250,"height":209},"granada2/granada2_00038":{"x":9.1,"y":105.7,"width":250,"height":209},"granada2/granada2_00039":{"x":9.1,"y":105.7,"width":250,"height":209}},"polvo":{"Comp 1/polvo_00002":{"x":4.97,"y":60.39,"width":250,"height":127},"Comp 1/polvo_00003":{"x":4.97,"y":60.39,"width":250,"height":127},"Comp 1/polvo_00004":{"x":4.97,"y":60.39,"width":250,"height":127},"Comp 1/polvo_00005":{"x":4.97,"y":60.39,"width":250,"height":127},"Comp 1/polvo_00006":{"x":4.97,"y":60.39,"width":250,"height":127},"Comp 1/polvo_00007":{"x":4.97,"y":60.39,"width":250,"height":127},"Comp 1/polvo_00008":{"x":4.97,"y":60.39,"width":250,"height":127},"Comp 1/polvo_00009":{"x":4.97,"y":60.39,"width":250,"height":127},"Comp 1/polvo_00010":{"x":4.97,"y":60.39,"width":250,"height":127},"Comp 1/polvo_00011":{"x":4.97,"y":60.39,"width":250,"height":127},"Comp 1/polvo_00012":{"x":4.97,"y":60.39,"width":250,"height":127},"Comp 1/polvo_00013":{"x":4.97,"y":60.39,"width":250,"height":127},"Comp 1/polvo_00014":{"x":4.97,"y":60.39,"width":250,"height":127},"Comp 1/polvo_00015":{"x":4.97,"y":60.39,"width":250,"height":127},"Comp 1/polvo_00016":{"x":4.97,"y":60.39,"width":250,"height":127},"Comp 1/polvo_00017":{"x":4.97,"y":60.39,"width":250,"height":127},"Comp 1/polvo_00018":{"x":4.97,"y":60.39,"width":250,"height":127},"Comp 1/polvo_00019":{"x":4.97,"y":60.39,"width":250,"height":127},"Comp 1/polvo_00020":{"x":4.97,"y":60.39,"width":250,"height":127},"Comp 1/polvo_00021":{"x":4.97,"y":60.39,"width":250,"height":127},"Comp 1/polvo_00022":{"x":4.97,"y":60.39,"width":250,"height":127},"Comp 1/polvo_00023":{"x":4.97,"y":60.39,"width":250,"height":127},"Comp 1/polvo_00024":{"x":4.97,"y":60.39,"width":250,"height":127},"Comp 1/polvo_00025":{"x":4.97,"y":60.39,"width":250,"height":127},"Comp 1/polvo_00026":{"x":4.97,"y":60.39,"width":250,"height":127},"Comp 1/polvo_00027":{"x":4.97,"y":60.39,"width":250,"height":127},"Comp 1/polvo_00028":{"x":4.97,"y":60.39,"width":250,"height":127},"Comp 1/polvo_00029":{"x":4.97,"y":60.39,"width":250,"height":127},"Comp 1/polvo_00030":{"x":4.97,"y":60.39,"width":250,"height":127},"Comp 1/polvo_00031":{"x":4.97,"y":60.39,"width":250,"height":127},"Comp 1/polvo_00032":{"x":4.97,"y":60.39,"width":250,"height":127}},"sombra":{"sombra":{"width":250,"height":79}}}},"events":{"bomba":{},"caidabomba":{}},"animations":{"BombaMortero":{"slots":{"sombra":{"color":[{"time":0,"color":"ffffff00"},{"time":0.3333,"color":"fffffffe"}]}},"bones":{"bone3":{"scale":[{"time":0,"x":5,"y":5,"curve":"stepped"},{"time":0.3333,"x":5,"y":5},{"time":3.3333,"x":0.5,"y":0.5}]}},"events":[{"time":0.0333,"name":"caidabomba"},{"time":3.3,"name":"bomba"}]},"FXGranada":{"slots":{"FXGranada":{"color":[{"time":0.9333,"color":"fffffffe"},{"time":1.7333,"color":"ffffff00"}],"attachment":[{"time":0,"name":"granada/granada_00003"},{"time":0.0333,"name":"granada/granada_00004"},{"time":0.0667,"name":"granada/granada_00005"},{"time":0.1,"name":"granada/granada_00006"},{"time":0.1333,"name":"granada/granada_00007"},{"time":0.1667,"name":"granada/granada_00008"},{"time":0.2,"name":"granada/granada_00009"},{"time":0.2333,"name":"granada/granada_00010"},{"time":0.2667,"name":"granada/granada_00011"},{"time":0.3,"name":"granada/granada_00012"},{"time":0.3333,"name":"granada/granada_00013"},{"time":0.3667,"name":"granada/granada_00014"},{"time":0.4,"name":"granada/granada_00015"},{"time":0.4333,"name":"granada/granada_00016"},{"time":0.4667,"name":"granada/granada_00017"},{"time":0.5,"name":"granada/granada_00018"},{"time":0.5333,"name":"granada/granada_00019"},{"time":0.5667,"name":"granada/granada_00020"},{"time":0.6,"name":"granada/granada_00021"},{"time":0.6333,"name":"granada/granada_00022"},{"time":0.6667,"name":"granada/granada_00023"},{"time":0.7,"name":"granada/granada_00024"},{"time":0.7333,"name":"granada/granada_00025"},{"time":0.7667,"name":"granada/granada_00026"},{"time":0.8,"name":"granada/granada_00027"},{"time":0.8333,"name":"granada/granada_00028"},{"time":0.8667,"name":"granada/granada_00029"},{"time":0.9,"name":"granada/granada_00030"},{"time":0.9333,"name":"granada/granada_00031"},{"time":0.9667,"name":"granada/granada_00032"},{"time":1,"name":"granada/granada_00033"},{"time":1.0333,"name":"granada/granada_00034"},{"time":1.0667,"name":"granada/granada_00035"},{"time":1.7333,"name":"granada/granada_00035"}]},"sombra":{"attachment":[{"time":0,"name":null}]}},"bones":{"bone":{"scale":[{"time":0.9333,"x":1,"y":1,"curve":[0.25,0,0.75,1]},{"time":1.7333,"x":0.667,"y":0.667}]}}},"FXGranada2":{"slots":{"FXGranada2":{"color":[{"time":1.2333,"color":"fffffffe","curve":[0.25,0,0.75,1]},{"time":1.7333,"color":"ffffff00"}],"attachment":[{"time":0,"name":"granada2/granada2_00002"},{"time":0.0333,"name":"granada2/granada2_00003"},{"time":0.0667,"name":"granada2/granada2_00004"},{"time":0.1,"name":"granada2/granada2_00005"},{"time":0.1333,"name":"granada2/granada2_00006"},{"time":0.1667,"name":"granada2/granada2_00007"},{"time":0.2,"name":"granada2/granada2_00008"},{"time":0.2333,"name":"granada2/granada2_00009"},{"time":0.2667,"name":"granada2/granada2_00010"},{"time":0.3,"name":"granada2/granada2_00011"},{"time":0.3333,"name":"granada2/granada2_00012"},{"time":0.3667,"name":"granada2/granada2_00013"},{"time":0.4,"name":"granada2/granada2_00014"},{"time":0.4333,"name":"granada2/granada2_00015"},{"time":0.4667,"name":"granada2/granada2_00016"},{"time":0.5,"name":"granada2/granada2_00017"},{"time":0.5333,"name":"granada2/granada2_00018"},{"time":0.5667,"name":"granada2/granada2_00019"},{"time":0.6,"name":"granada2/granada2_00020"},{"time":0.6333,"name":"granada2/granada2_00021"},{"time":0.6667,"name":"granada2/granada2_00022"},{"time":0.7,"name":"granada2/granada2_00023"},{"time":0.7333,"name":"granada2/granada2_00024"},{"time":0.7667,"name":"granada2/granada2_00025"},{"time":0.8,"name":"granada2/granada2_00026"},{"time":0.8333,"name":"granada2/granada2_00027"},{"time":0.8667,"name":"granada2/granada2_00028"},{"time":0.9,"name":"granada2/granada2_00029"},{"time":0.9333,"name":"granada2/granada2_00030"},{"time":0.9667,"name":"granada2/granada2_00031"},{"time":1,"name":"granada2/granada2_00032"},{"time":1.0333,"name":"granada2/granada2_00033"},{"time":1.0667,"name":"granada2/granada2_00034"},{"time":1.1,"name":"granada2/granada2_00035"},{"time":1.1333,"name":"granada2/granada2_00036"},{"time":1.1667,"name":"granada2/granada2_00037"},{"time":1.2,"name":"granada2/granada2_00038"},{"time":1.2333,"name":"granada2/granada2_00039"}]},"sombra":{"attachment":[{"time":0,"name":null}]}},"bones":{"bone2":{"scale":[{"time":1.2333,"x":1,"y":1,"curve":[0.25,0,0.75,1]},{"time":1.7333,"x":0,"y":0}]}}},"polvo":{"slots":{"polvo":{"color":[{"time":0,"color":"ffbc14ff"},{"time":0.5333,"color":"ffffffff"},{"time":1,"color":"ffffff00"}],"attachment":[{"time":0,"name":"Comp 1/polvo_00002"},{"time":0.0333,"name":"Comp 1/polvo_00003"},{"time":0.0667,"name":"Comp 1/polvo_00004"},{"time":0.1,"name":"Comp 1/polvo_00005"},{"time":0.1333,"name":"Comp 1/polvo_00006"},{"time":0.1667,"name":"Comp 1/polvo_00007"},{"time":0.2,"name":"Comp 1/polvo_00008"},{"time":0.2333,"name":"Comp 1/polvo_00009"},{"time":0.2667,"name":"Comp 1/polvo_00010"},{"time":0.3,"name":"Comp 1/polvo_00011"},{"time":0.3333,"name":"Comp 1/polvo_00012"},{"time":0.3667,"name":"Comp 1/polvo_00013"},{"time":0.4,"name":"Comp 1/polvo_00014"},{"time":0.4333,"name":"Comp 1/polvo_00015"},{"time":0.4667,"name":"Comp 1/polvo_00016"},{"time":0.5,"name":"Comp 1/polvo_00017"},{"time":0.5333,"name":"Comp 1/polvo_00018"},{"time":0.5667,"name":"Comp 1/polvo_00019"},{"time":0.6,"name":"Comp 1/polvo_00020"},{"time":0.6333,"name":"Comp 1/polvo_00021"},{"time":0.6667,"name":"Comp 1/polvo_00022"},{"time":0.7,"name":"Comp 1/polvo_00023"},{"time":0.7333,"name":"Comp 1/polvo_00024"},{"time":0.7667,"name":"Comp 1/polvo_00025"},{"time":0.8,"name":"Comp 1/polvo_00026"},{"time":0.8333,"name":"Comp 1/polvo_00027"},{"time":0.8667,"name":"Comp 1/polvo_00028"},{"time":0.9,"name":"Comp 1/polvo_00029"},{"time":0.9333,"name":"Comp 1/polvo_00030"},{"time":0.9667,"name":"Comp 1/polvo_00031"},{"time":1,"name":"Comp 1/polvo_00032"}]},"sombra":{"attachment":[{"time":0,"name":null}]}}}}}